<?xml version="1.0" encoding="UTF-8" ?>
<!DOCTYPE mapper PUBLIC "-//mybatis.org//DTD Mapper 3.0//EN" "http://mybatis.org/dtd/mybatis-3-mapper.dtd" >
<mapper namespace="tang.ming.qiao.mapper.UserInfoMapper" >
  <resultMap id="BaseResultMap" type="tang.ming.qiao.domain.UserInfo" >
    <!--
      WARNING - @mbggenerated
      This element is automatically generated by MyBatis Generator, do not modify.
    -->
    <id column="id" property="id" jdbcType="BIGINT" />
    <result column="user_name" property="userName" jdbcType="VARCHAR" />
    <result column="account" property="account" jdbcType="VARCHAR" />
    <result column="nickname" property="nickname" jdbcType="VARCHAR" />
    <result column="password" property="password" jdbcType="VARCHAR" />
    <result column="amount" property="amount" jdbcType="INTEGER" />
    <result column="credits" property="credits" jdbcType="INTEGER" />
    <result column="status" property="status" jdbcType="TINYINT" />
    <result column="telephone" property="telephone" jdbcType="VARCHAR" />
    <result column="sex" property="sex" jdbcType="TINYINT" />
    <result column="grade" property="grade" jdbcType="TINYINT" />
    <result column="birthday" property="birthday" jdbcType="DATE" />
    <result column="province" property="province" jdbcType="VARCHAR" />
    <result column="city" property="city" jdbcType="VARCHAR" />
    <result column="zone" property="zone" jdbcType="VARCHAR" />
    <result column="school" property="school" jdbcType="VARCHAR" />
    <result column="reg_time" property="regTime" jdbcType="TIMESTAMP" />
    <result column="del_time" property="delTime" jdbcType="TIMESTAMP" />
    <result column="last_login" property="lastLogin" jdbcType="TIMESTAMP" />
    <result column="big_icon" property="bigIcon" jdbcType="VARCHAR" />
    <result column="mid_icon" property="midIcon" jdbcType="VARCHAR" />
    <result column="small_icon" property="smallIcon" jdbcType="VARCHAR" />
  </resultMap>
  <sql id="Example_Where_Clause" >
    <!--
      WARNING - @mbggenerated
      This element is automatically generated by MyBatis Generator, do not modify.
    -->
    <where >
      <foreach collection="oredCriteria" item="criteria" separator="or" >
        <if test="criteria.valid" >
          <trim prefix="(" suffix=")" prefixOverrides="and" >
            <foreach collection="criteria.criteria" item="criterion" >
              <choose >
                <when test="criterion.noValue" >
                  and ${criterion.condition}
                </when>
                <when test="criterion.singleValue" >
                  and ${criterion.condition} #{criterion.value}
                </when>
                <when test="criterion.betweenValue" >
                  and ${criterion.condition} #{criterion.value} and #{criterion.secondValue}
                </when>
                <when test="criterion.listValue" >
                  and ${criterion.condition}
                  <foreach collection="criterion.value" item="listItem" open="(" close=")" separator="," >
                    #{listItem}
                  </foreach>
                </when>
              </choose>
            </foreach>
          </trim>
        </if>
      </foreach>
    </where>
  </sql>
  <sql id="Update_By_Example_Where_Clause" >
    <!--
      WARNING - @mbggenerated
      This element is automatically generated by MyBatis Generator, do not modify.
    -->
    <where >
      <foreach collection="example.oredCriteria" item="criteria" separator="or" >
        <if test="criteria.valid" >
          <trim prefix="(" suffix=")" prefixOverrides="and" >
            <foreach collection="criteria.criteria" item="criterion" >
              <choose >
                <when test="criterion.noValue" >
                  and ${criterion.condition}
                </when>
                <when test="criterion.singleValue" >
                  and ${criterion.condition} #{criterion.value}
                </when>
                <when test="criterion.betweenValue" >
                  and ${criterion.condition} #{criterion.value} and #{criterion.secondValue}
                </when>
                <when test="criterion.listValue" >
                  and ${criterion.condition}
                  <foreach collection="criterion.value" item="listItem" open="(" close=")" separator="," >
                    #{listItem}
                  </foreach>
                </when>
              </choose>
            </foreach>
          </trim>
        </if>
      </foreach>
    </where>
  </sql>
  <sql id="Base_Column_List" >
    <!--
      WARNING - @mbggenerated
      This element is automatically generated by MyBatis Generator, do not modify.
    -->
    id, user_name, account, nickname, password, amount, credits, status, telephone, sex, 
    grade, birthday, province, city, zone, school, reg_time, del_time, last_login, big_icon, 
    mid_icon, small_icon
  </sql>
  <select id="selectByExample" resultMap="BaseResultMap" parameterType="tang.ming.qiao.domain.UserInfoExample" >
    <!--
      WARNING - @mbggenerated
      This element is automatically generated by MyBatis Generator, do not modify.
    -->
    select
    <if test="distinct" >
      distinct
    </if>
    <include refid="Base_Column_List" />
    from user_info
    <if test="_parameter != null" >
      <include refid="Example_Where_Clause" />
    </if>
    <if test="orderByClause != null" >
      order by ${orderByClause}
    </if>
  </select>
  <select id="selectByPrimaryKey" resultMap="BaseResultMap" parameterType="java.lang.Long" >
    <!--
      WARNING - @mbggenerated
      This element is automatically generated by MyBatis Generator, do not modify.
    -->
    select 
    <include refid="Base_Column_List" />
    from user_info
    where id = #{id,jdbcType=BIGINT}
  </select>
  <delete id="deleteByPrimaryKey" parameterType="java.lang.Long" >
    <!--
      WARNING - @mbggenerated
      This element is automatically generated by MyBatis Generator, do not modify.
    -->
    delete from user_info
    where id = #{id,jdbcType=BIGINT}
  </delete>
  <delete id="deleteByExample" parameterType="tang.ming.qiao.domain.UserInfoExample" >
    <!--
      WARNING - @mbggenerated
      This element is automatically generated by MyBatis Generator, do not modify.
    -->
    delete from user_info
    <if test="_parameter != null" >
      <include refid="Example_Where_Clause" />
    </if>
  </delete>
  <insert id="insert" parameterType="tang.ming.qiao.domain.UserInfo" >
    <!--
      WARNING - @mbggenerated
      This element is automatically generated by MyBatis Generator, do not modify.
    -->
    insert into user_info (id, user_name, account, 
      nickname, password, amount, 
      credits, status, telephone, 
      sex, grade, birthday, 
      province, city, zone, 
      school, reg_time, del_time, 
      last_login, big_icon, mid_icon, 
      small_icon)
    values (#{id,jdbcType=BIGINT}, #{userName,jdbcType=VARCHAR}, #{account,jdbcType=VARCHAR}, 
      #{nickname,jdbcType=VARCHAR}, #{password,jdbcType=VARCHAR}, #{amount,jdbcType=INTEGER}, 
      #{credits,jdbcType=INTEGER}, #{status,jdbcType=TINYINT}, #{telephone,jdbcType=VARCHAR}, 
      #{sex,jdbcType=TINYINT}, #{grade,jdbcType=TINYINT}, #{birthday,jdbcType=DATE}, 
      #{province,jdbcType=VARCHAR}, #{city,jdbcType=VARCHAR}, #{zone,jdbcType=VARCHAR}, 
      #{school,jdbcType=VARCHAR}, #{regTime,jdbcType=TIMESTAMP}, #{delTime,jdbcType=TIMESTAMP}, 
      #{lastLogin,jdbcType=TIMESTAMP}, #{bigIcon,jdbcType=VARCHAR}, #{midIcon,jdbcType=VARCHAR}, 
      #{smallIcon,jdbcType=VARCHAR})
  </insert>
  <insert id="insertSelective" parameterType="tang.ming.qiao.domain.UserInfo" >
    <!--
      WARNING - @mbggenerated
      This element is automatically generated by MyBatis Generator, do not modify.
    -->
    insert into user_info
    <trim prefix="(" suffix=")" suffixOverrides="," >
      <if test="id != null" >
        id,
      </if>
      <if test="userName != null" >
        user_name,
      </if>
      <if test="account != null" >
        account,
      </if>
      <if test="nickname != null" >
        nickname,
      </if>
      <if test="password != null" >
        password,
      </if>
      <if test="amount != null" >
        amount,
      </if>
      <if test="credits != null" >
        credits,
      </if>
      <if test="status != null" >
        status,
      </if>
      <if test="telephone != null" >
        telephone,
      </if>
      <if test="sex != null" >
        sex,
      </if>
      <if test="grade != null" >
        grade,
      </if>
      <if test="birthday != null" >
        birthday,
      </if>
      <if test="province != null" >
        province,
      </if>
      <if test="city != null" >
        city,
      </if>
      <if test="zone != null" >
        zone,
      </if>
      <if test="school != null" >
        school,
      </if>
      <if test="regTime != null" >
        reg_time,
      </if>
      <if test="delTime != null" >
        del_time,
      </if>
      <if test="lastLogin != null" >
        last_login,
      </if>
      <if test="bigIcon != null" >
        big_icon,
      </if>
      <if test="midIcon != null" >
        mid_icon,
      </if>
      <if test="smallIcon != null" >
        small_icon,
      </if>
    </trim>
    <trim prefix="values (" suffix=")" suffixOverrides="," >
      <if test="id != null" >
        #{id,jdbcType=BIGINT},
      </if>
      <if test="userName != null" >
        #{userName,jdbcType=VARCHAR},
      </if>
      <if test="account != null" >
        #{account,jdbcType=VARCHAR},
      </if>
      <if test="nickname != null" >
        #{nickname,jdbcType=VARCHAR},
      </if>
      <if test="password != null" >
        #{password,jdbcType=VARCHAR},
      </if>
      <if test="amount != null" >
        #{amount,jdbcType=INTEGER},
      </if>
      <if test="credits != null" >
        #{credits,jdbcType=INTEGER},
      </if>
      <if test="status != null" >
        #{status,jdbcType=TINYINT},
      </if>
      <if test="telephone != null" >
        #{telephone,jdbcType=VARCHAR},
      </if>
      <if test="sex != null" >
        #{sex,jdbcType=TINYINT},
      </if>
      <if test="grade != null" >
        #{grade,jdbcType=TINYINT},
      </if>
      <if test="birthday != null" >
        #{birthday,jdbcType=DATE},
      </if>
      <if test="province != null" >
        #{province,jdbcType=VARCHAR},
      </if>
      <if test="city != null" >
        #{city,jdbcType=VARCHAR},
      </if>
      <if test="zone != null" >
        #{zone,jdbcType=VARCHAR},
      </if>
      <if test="school != null" >
        #{school,jdbcType=VARCHAR},
      </if>
      <if test="regTime != null" >
        #{regTime,jdbcType=TIMESTAMP},
      </if>
      <if test="delTime != null" >
        #{delTime,jdbcType=TIMESTAMP},
      </if>
      <if test="lastLogin != null" >
        #{lastLogin,jdbcType=TIMESTAMP},
      </if>
      <if test="bigIcon != null" >
        #{bigIcon,jdbcType=VARCHAR},
      </if>
      <if test="midIcon != null" >
        #{midIcon,jdbcType=VARCHAR},
      </if>
      <if test="smallIcon != null" >
        #{smallIcon,jdbcType=VARCHAR},
      </if>
    </trim>
  </insert>
  <select id="countByExample" parameterType="tang.ming.qiao.domain.UserInfoExample" resultType="java.lang.Integer" >
    <!--
      WARNING - @mbggenerated
      This element is automatically generated by MyBatis Generator, do not modify.
    -->
    select count(*) from user_info
    <if test="_parameter != null" >
      <include refid="Example_Where_Clause" />
    </if>
  </select>
  <update id="updateByExampleSelective" parameterType="map" >
    <!--
      WARNING - @mbggenerated
      This element is automatically generated by MyBatis Generator, do not modify.
    -->
    update user_info
    <set >
      <if test="record.id != null" >
        id = #{record.id,jdbcType=BIGINT},
      </if>
      <if test="record.userName != null" >
        user_name = #{record.userName,jdbcType=VARCHAR},
      </if>
      <if test="record.account != null" >
        account = #{record.account,jdbcType=VARCHAR},
      </if>
      <if test="record.nickname != null" >
        nickname = #{record.nickname,jdbcType=VARCHAR},
      </if>
      <if test="record.password != null" >
        password = #{record.password,jdbcType=VARCHAR},
      </if>
      <if test="record.amount != null" >
        amount = #{record.amount,jdbcType=INTEGER},
      </if>
      <if test="record.credits != null" >
        credits = #{record.credits,jdbcType=INTEGER},
      </if>
      <if test="record.status != null" >
        status = #{record.status,jdbcType=TINYINT},
      </if>
      <if test="record.telephone != null" >
        telephone = #{record.telephone,jdbcType=VARCHAR},
      </if>
      <if test="record.sex != null" >
        sex = #{record.sex,jdbcType=TINYINT},
      </if>
      <if test="record.grade != null" >
        grade = #{record.grade,jdbcType=TINYINT},
      </if>
      <if test="record.birthday != null" >
        birthday = #{record.birthday,jdbcType=DATE},
      </if>
      <if test="record.province != null" >
        province = #{record.province,jdbcType=VARCHAR},
      </if>
      <if test="record.city != null" >
        city = #{record.city,jdbcType=VARCHAR},
      </if>
      <if test="record.zone != null" >
        zone = #{record.zone,jdbcType=VARCHAR},
      </if>
      <if test="record.school != null" >
        school = #{record.school,jdbcType=VARCHAR},
      </if>
      <if test="record.regTime != null" >
        reg_time = #{record.regTime,jdbcType=TIMESTAMP},
      </if>
      <if test="record.delTime != null" >
        del_time = #{record.delTime,jdbcType=TIMESTAMP},
      </if>
      <if test="record.lastLogin != null" >
        last_login = #{record.lastLogin,jdbcType=TIMESTAMP},
      </if>
      <if test="record.bigIcon != null" >
        big_icon = #{record.bigIcon,jdbcType=VARCHAR},
      </if>
      <if test="record.midIcon != null" >
        mid_icon = #{record.midIcon,jdbcType=VARCHAR},
      </if>
      <if test="record.smallIcon != null" >
        small_icon = #{record.smallIcon,jdbcType=VARCHAR},
      </if>
    </set>
    <if test="_parameter != null" >
      <include refid="Update_By_Example_Where_Clause" />
    </if>
  </update>
  <update id="updateByExample" parameterType="map" >
    <!--
      WARNING - @mbggenerated
      This element is automatically generated by MyBatis Generator, do not modify.
    -->
    update user_info
    set id = #{record.id,jdbcType=BIGINT},
      user_name = #{record.userName,jdbcType=VARCHAR},
      account = #{record.account,jdbcType=VARCHAR},
      nickname = #{record.nickname,jdbcType=VARCHAR},
      password = #{record.password,jdbcType=VARCHAR},
      amount = #{record.amount,jdbcType=INTEGER},
      credits = #{record.credits,jdbcType=INTEGER},
      status = #{record.status,jdbcType=TINYINT},
      telephone = #{record.telephone,jdbcType=VARCHAR},
      sex = #{record.sex,jdbcType=TINYINT},
      grade = #{record.grade,jdbcType=TINYINT},
      birthday = #{record.birthday,jdbcType=DATE},
      province = #{record.province,jdbcType=VARCHAR},
      city = #{record.city,jdbcType=VARCHAR},
      zone = #{record.zone,jdbcType=VARCHAR},
      school = #{record.school,jdbcType=VARCHAR},
      reg_time = #{record.regTime,jdbcType=TIMESTAMP},
      del_time = #{record.delTime,jdbcType=TIMESTAMP},
      last_login = #{record.lastLogin,jdbcType=TIMESTAMP},
      big_icon = #{record.bigIcon,jdbcType=VARCHAR},
      mid_icon = #{record.midIcon,jdbcType=VARCHAR},
      small_icon = #{record.smallIcon,jdbcType=VARCHAR}
    <if test="_parameter != null" >
      <include refid="Update_By_Example_Where_Clause" />
    </if>
  </update>
  <update id="updateByPrimaryKeySelective" parameterType="tang.ming.qiao.domain.UserInfo" >
    <!--
      WARNING - @mbggenerated
      This element is automatically generated by MyBatis Generator, do not modify.
    -->
    update user_info
    <set >
      <if test="userName != null" >
        user_name = #{userName,jdbcType=VARCHAR},
      </if>
      <if test="account != null" >
        account = #{account,jdbcType=VARCHAR},
      </if>
      <if test="nickname != null" >
        nickname = #{nickname,jdbcType=VARCHAR},
      </if>
      <if test="password != null" >
        password = #{password,jdbcType=VARCHAR},
      </if>
      <if test="amount != null" >
        amount = #{amount,jdbcType=INTEGER},
      </if>
      <if test="credits != null" >
        credits = #{credits,jdbcType=INTEGER},
      </if>
      <if test="status != null" >
        status = #{status,jdbcType=TINYINT},
      </if>
      <if test="telephone != null" >
        telephone = #{telephone,jdbcType=VARCHAR},
      </if>
      <if test="sex != null" >
        sex = #{sex,jdbcType=TINYINT},
      </if>
      <if test="grade != null" >
        grade = #{grade,jdbcType=TINYINT},
      </if>
      <if test="birthday != null" >
        birthday = #{birthday,jdbcType=DATE},
      </if>
      <if test="province != null" >
        province = #{province,jdbcType=VARCHAR},
      </if>
      <if test="city != null" >
        city = #{city,jdbcType=VARCHAR},
      </if>
      <if test="zone != null" >
        zone = #{zone,jdbcType=VARCHAR},
      </if>
      <if test="school != null" >
        school = #{school,jdbcType=VARCHAR},
      </if>
      <if test="regTime != null" >
        reg_time = #{regTime,jdbcType=TIMESTAMP},
      </if>
      <if test="delTime != null" >
        del_time = #{delTime,jdbcType=TIMESTAMP},
      </if>
      <if test="lastLogin != null" >
        last_login = #{lastLogin,jdbcType=TIMESTAMP},
      </if>
      <if test="bigIcon != null" >
        big_icon = #{bigIcon,jdbcType=VARCHAR},
      </if>
      <if test="midIcon != null" >
        mid_icon = #{midIcon,jdbcType=VARCHAR},
      </if>
      <if test="smallIcon != null" >
        small_icon = #{smallIcon,jdbcType=VARCHAR},
      </if>
    </set>
    where id = #{id,jdbcType=BIGINT}
  </update>
  <update id="updateByPrimaryKey" parameterType="tang.ming.qiao.domain.UserInfo" >
    <!--
      WARNING - @mbggenerated
      This element is automatically generated by MyBatis Generator, do not modify.
    -->
    update user_info
    set user_name = #{userName,jdbcType=VARCHAR},
      account = #{account,jdbcType=VARCHAR},
      nickname = #{nickname,jdbcType=VARCHAR},
      password = #{password,jdbcType=VARCHAR},
      amount = #{amount,jdbcType=INTEGER},
      credits = #{credits,jdbcType=INTEGER},
      status = #{status,jdbcType=TINYINT},
      telephone = #{telephone,jdbcType=VARCHAR},
      sex = #{sex,jdbcType=TINYINT},
      grade = #{grade,jdbcType=TINYINT},
      birthday = #{birthday,jdbcType=DATE},
      province = #{province,jdbcType=VARCHAR},
      city = #{city,jdbcType=VARCHAR},
      zone = #{zone,jdbcType=VARCHAR},
      school = #{school,jdbcType=VARCHAR},
      reg_time = #{regTime,jdbcType=TIMESTAMP},
      del_time = #{delTime,jdbcType=TIMESTAMP},
      last_login = #{lastLogin,jdbcType=TIMESTAMP},
      big_icon = #{bigIcon,jdbcType=VARCHAR},
      mid_icon = #{midIcon,jdbcType=VARCHAR},
      small_icon = #{smallIcon,jdbcType=VARCHAR}
    where id = #{id,jdbcType=BIGINT}
  </update>
</mapper>